{
  "ComponentIndexes": {},
  "ControlUniqueGuids": {},
  "ControlUniqueIds": {
    "App": 1,
    "Attachments_DataCard1": 112,
    "btnCancelNo": 162,
    "btnCancelRequest": 177,
    "btnCancelYes": 161,
    "btnConfirmCancel": 155,
    "btnConfirmEstimate": 176,
    "btnConfirmYes": 154,
    "btnGetStarted": 16,
    "btnNavHome": 133,
    "btnNavHome2": 143,
    "btnNavHomeActive": 25,
    "btnNavMyRequests": 135,
    "btnNavMyRequests2": 145,
    "btnNavMyRequestsHome": 27,
    "btnNavSubmit": 134,
    "btnNavSubmit2": 144,
    "btnNavSubmitHome": 26,
    "btnRefresh": 140,
    "btnStatusBadge": 168,
    "btnSubmit": 130,
    "btnViewRequests": 21,
    "cirColorPreview": 100,
    "cirColorPreviewBackdrop": 99,
    "cirPrintColorBackdrop": 171,
    "cirPrintColorDot": 172,
    "Color_DataCard1": 94,
    "conActionCards": 11,
    "conCancelModal": 156,
    "conConfirmModal": 146,
    "conFormArea": 36,
    "conGalleryArea": 164,
    "conHeader": 29,
    "conHeader2": 137,
    "conHeaderHome": 5,
    "conLoadingOverlay": 32,
    "conNavBar": 131,
    "conNavBar2": 141,
    "conNavBarHome": 23,
    "conRequestsCard": 17,
    "conSubmitCard": 12,
    "conWelcome": 8,
    "Course Number_DataCard1": 70,
    "DataCardKey1": 42,
    "DataCardKey10": 89,
    "DataCardKey11": 104,
    "DataCardKey12": 109,
    "DataCardKey13": 126,
    "DataCardKey2": 121,
    "DataCardKey3": 47,
    "DataCardKey31": 58,
    "DataCardKey32": 114,
    "DataCardKey4": 53,
    "DataCardKey5": 72,
    "DataCardKey6": 66,
    "DataCardKey7": 77,
    "DataCardKey8": 82,
    "DataCardKey9": 96,
    "DataCardValue1": 43,
    "DataCardValue10": 91,
    "DataCardValue11": 105,
    "DataCardValue12": 110,
    "DataCardValue13": 127,
    "DataCardValue2": 122,
    "DataCardValue3": 48,
    "DataCardValue30": 60,
    "DataCardValue31": 117,
    "DataCardValue4": 54,
    "DataCardValue5": 73,
    "DataCardValue6": 68,
    "DataCardValue7": 78,
    "DataCardValue8": 84,
    "DataCardValue9": 98,
    "dcImportantInfo": 38,
    "Discipline_DataCard1": 64,
    "DueDate_DataCard1": 102,
    "ErrorMessage1": 44,
    "ErrorMessage10": 92,
    "ErrorMessage11": 106,
    "ErrorMessage12": 111,
    "ErrorMessage13": 128,
    "ErrorMessage2": 123,
    "ErrorMessage3": 50,
    "ErrorMessage31": 61,
    "ErrorMessage32": 118,
    "ErrorMessage4": 55,
    "ErrorMessage5": 74,
    "ErrorMessage6": 69,
    "ErrorMessage7": 79,
    "ErrorMessage8": 85,
    "ErrorMessage9": 101,
    "frmSubmit": 37,
    "galleryTemplate1": 166,
    "galMyRequests": 165,
    "Host": 3,
    "icnRequests": 18,
    "icnSubmit": 13,
    "imgTigerCardExample": 63,
    "Label1": 67,
    "lblAttachmentsRequired": 116,
    "lblCancelMessage": 160,
    "lblCancelTitle": 158,
    "lblColorRequired": 97,
    "lblConfirmCost": 150,
    "lblConfirmDetails": 152,
    "lblConfirmReqKey": 149,
    "lblConfirmTitle": 148,
    "lblConfirmWarning": 153,
    "lblDimensionsWarning": 93,
    "lblEmptyState": 163,
    "lblEstimate": 174,
    "lblFileWarning": 115,
    "lblHeaderTitle": 31,
    "lblHeaderTitle2": 139,
    "lblHeaderTitleHome": 7,
    "lblHelpText": 22,
    "lblImportantInfo": 39,
    "lblLoadingText": 35,
    "lblMethodInfo": 86,
    "lblMethodRequired": 83,
    "lblPrintDetails": 173,
    "lblPrinterRequired": 90,
    "lblReqKey": 169,
    "lblRequestsDesc": 20,
    "lblRequestsTitle": 19,
    "lblStatusMessage": 175,
    "lblStudentName": 49,
    "lblSubmitDate": 170,
    "lblSubmitDesc": 15,
    "lblSubmitTitle": 14,
    "lblSubtitle": 10,
    "lblTigerCardError": 62,
    "lblTigerCardRequired": 59,
    "lblValidationMessage": 129,
    "lblWelcome": 9,
    "Method_DataCard1": 80,
    "Notes_DataCard1": 107,
    "Printer_DataCard1": 87,
    "ProjectType_DataCard1": 75,
    "recCancelModal": 157,
    "recCancelOverlay": 159,
    "recCardBg": 167,
    "recConfirmModal": 147,
    "recConfirmOverlay": 151,
    "recHeaderBg": 30,
    "recHeaderBg2": 138,
    "recHeaderBgHome": 6,
    "recLoadingBg": 34,
    "recLoadingOverlay": 33,
    "recNavBg": 132,
    "recNavBg2": 142,
    "recNavBgHome": 24,
    "scrHome": 4,
    "scrMyRequests": 136,
    "scrSubmit": 28,
    "StarVisible1": 41,
    "StarVisible10": 88,
    "StarVisible11": 103,
    "StarVisible12": 108,
    "StarVisible13": 125,
    "StarVisible2": 120,
    "StarVisible3": 46,
    "StarVisible31": 57,
    "StarVisible32": 113,
    "StarVisible4": 52,
    "StarVisible5": 71,
    "StarVisible6": 65,
    "StarVisible7": 76,
    "StarVisible8": 81,
    "StarVisible9": 95,
    "Status_DataCard1": 124,
    "Student_DataCard1": 45,
    "StudentEmail_DataCard1": 51,
    "StudentEntraId_DataCard1": 119,
    "TigerCardNumber_DataCard1": 56,
    "Title_DataCard1": 40
  },
  "FunctionParamsInvariantScripts": {},
  "FunctionParamsInvariantScriptsOnInstances": {},
  "HeaderLastSavedDateTimeUTC": "04/13/2026 16:01:19",
  "IsLegacyComponentAllowGlobalScopeCase": false,
  "LocalConnectionIDReferences": {
    "1daf1760-d2c4-4dbd-b72a-6169cf6b2b3a": "\"/providers/microsoft.powerapps/apis/shared_sharepointonline/connections/shared-sharepointonl-5ffd63e3-3cf7-406d-9044-1818c6c1ee2d\"",
    "fe74612e-4945-4ac5-9aab-ed55515a90b3": "\"/providers/microsoft.powerapps/apis/shared_office365users/connections/shared-office365user-8db9a1f9-e1f7-4196-9d7c-a4a8c24998e0\""
  },
  "LocalDatabaseReferencesAsEmpty": true,
  "LocalResourceFileNames": {
    "Tiger Card": "ebbf5aca-1db1-47af-bb05-8755b6761eaf.jpeg",
    "TigerCard": "69afd027-08b8-40f2-8363-5bb1d7dbf4a3.png"
  },
  "LocalResourceRootPaths": {
    "Tiger Card": "https://dsprdil106wus.blob.core.windows.net/ab33f30a-8025-4efd-be99-992db9fbd5c8-1/resource/ZWJiZjVhY2EtMWRiMS00N2FmLWJiMDUtODc1NWI2NzYxZWFm.jpeg?skoid=58690ece-ec83-4ce2-9ce8-883d4d6a54ee&sktid=975f013f-7f24-47e8-a7d3-abc4752bf346&skt=2026-04-13T16%3A00%3A24Z&ske=2026-04-14T16%3A15%3A24Z&sks=b&skv=2023-01-03&sv=2023-01-03&spr=https&se=2026-04-14T16%3A15%3A24Z&sr=b&sp=r&sig=I0bYzmqsVnPZ7lx5Nfb8UDH0Ur%2Fo5nx8IxuBOM6Uh28%3D",
    "TigerCard": "https://dsprdil106wus.blob.core.windows.net/ab33f30a-8025-4efd-be99-992db9fbd5c8-1/resource/NjlhZmQwMjctMDhiOC00MGYyLTgzNjMtNWJiMWQ3ZGJmNGEz.png?skoid=58690ece-ec83-4ce2-9ce8-883d4d6a54ee&sktid=975f013f-7f24-47e8-a7d3-abc4752bf346&skt=2026-04-13T16%3A00%3A24Z&ske=2026-04-14T16%3A15%3A24Z&sks=b&skv=2023-01-03&sv=2023-01-03&spr=https&se=2026-04-14T16%3A15%3A24Z&sr=b&sp=r&sig=RrjJm7RgJc9N8JRq2lvJyWuyEdRcNXIEXmRBD8rXRfI%3D"
  },
  "OldLogoFileName": "grgprwn3.jpg",
  "OrderComponentMetadata": {},
  "OrderComponentTemplate": {},
  "OrderDataSource": {
    "ComboBoxSample": 2,
    "CustomGallerySample": 4,
    "DropDownSample": 3,
    "Office365Users": 0,
    "PrintRequests": 1
  },
  "OrderGroupControls": {},
  "OrderPcfTemplate": {},
  "OrderTemplate": {},
  "OrderXMLTemplate": {
    "attachments": 11,
    "button": 4,
    "circle": 9,
    "combobox": 7,
    "datepicker": 10,
    "form": 5,
    "gallery": 12,
    "groupContainer": 0,
    "icon": 3,
    "image": 8,
    "label": 2,
    "rectangle": 1,
    "text": 6
  },
  "OverridablePropertiesEntry": {
    "App": {},
    "Attachments_DataCard1": {},
    "btnCancelNo": {},
    "btnCancelRequest": {},
    "btnCancelYes": {},
    "btnConfirmCancel": {},
    "btnConfirmEstimate": {},
    "btnConfirmYes": {},
    "btnGetStarted": {},
    "btnNavHome": {},
    "btnNavHome2": {},
    "btnNavHomeActive": {},
    "btnNavMyRequests": {},
    "btnNavMyRequests2": {},
    "btnNavMyRequestsHome": {},
    "btnNavSubmit": {},
    "btnNavSubmit2": {},
    "btnNavSubmitHome": {},
    "btnRefresh": {},
    "btnStatusBadge": {},
    "btnSubmit": {},
    "btnViewRequests": {},
    "cirColorPreview": {},
    "cirColorPreviewBackdrop": {},
    "cirPrintColorBackdrop": {},
    "cirPrintColorDot": {},
    "Color_DataCard1": {},
    "conActionCards": {},
    "conCancelModal": {},
    "conConfirmModal": {},
    "conFormArea": {},
    "conGalleryArea": {},
    "conHeader": {},
    "conHeader2": {},
    "conHeaderHome": {},
    "conLoadingOverlay": {},
    "conNavBar": {},
    "conNavBar2": {},
    "conNavBarHome": {},
    "conRequestsCard": {},
    "conSubmitCard": {},
    "conWelcome": {},
    "Course Number_DataCard1": {},
    "DataCardKey1": {},
    "DataCardKey10": {},
    "DataCardKey11": {},
    "DataCardKey12": {},
    "DataCardKey13": {},
    "DataCardKey2": {},
    "DataCardKey3": {},
    "DataCardKey31": {},
    "DataCardKey32": {},
    "DataCardKey4": {},
    "DataCardKey5": {},
    "DataCardKey6": {},
    "DataCardKey7": {},
    "DataCardKey8": {},
    "DataCardKey9": {},
    "DataCardValue1": {},
    "DataCardValue10": {},
    "DataCardValue11": {},
    "DataCardValue12": {},
    "DataCardValue13": {},
    "DataCardValue2": {},
    "DataCardValue3": {},
    "DataCardValue30": {},
    "DataCardValue31": {},
    "DataCardValue4": {},
    "DataCardValue5": {},
    "DataCardValue6": {},
    "DataCardValue7": {},
    "DataCardValue8": {},
    "DataCardValue9": {},
    "dcImportantInfo": {},
    "Discipline_DataCard1": {},
    "DueDate_DataCard1": {},
    "ErrorMessage1": {},
    "ErrorMessage10": {},
    "ErrorMessage11": {},
    "ErrorMessage12": {},
    "ErrorMessage13": {},
    "ErrorMessage2": {},
    "ErrorMessage3": {},
    "ErrorMessage31": {},
    "ErrorMessage32": {},
    "ErrorMessage4": {},
    "ErrorMessage5": {},
    "ErrorMessage6": {},
    "ErrorMessage7": {},
    "ErrorMessage8": {},
    "ErrorMessage9": {},
    "frmSubmit": {},
    "galleryTemplate1": {},
    "galMyRequests": {},
    "Host": {},
    "icnRequests": {},
    "icnSubmit": {},
    "imgTigerCardExample": {},
    "Label1": {},
    "lblAttachmentsRequired": {},
    "lblCancelMessage": {},
    "lblCancelTitle": {},
    "lblColorRequired": {},
    "lblConfirmCost": {},
    "lblConfirmDetails": {},
    "lblConfirmReqKey": {},
    "lblConfirmTitle": {},
    "lblConfirmWarning": {},
    "lblDimensionsWarning": {},
    "lblEmptyState": {},
    "lblEstimate": {},
    "lblFileWarning": {},
    "lblHeaderTitle": {},
    "lblHeaderTitle2": {},
    "lblHeaderTitleHome": {},
    "lblHelpText": {},
    "lblImportantInfo": {},
    "lblLoadingText": {},
    "lblMethodInfo": {},
    "lblMethodRequired": {},
    "lblPrintDetails": {},
    "lblPrinterRequired": {},
    "lblReqKey": {},
    "lblRequestsDesc": {},
    "lblRequestsTitle": {},
    "lblStatusMessage": {},
    "lblStudentName": {},
    "lblSubmitDate": {},
    "lblSubmitDesc": {},
    "lblSubmitTitle": {},
    "lblSubtitle": {},
    "lblTigerCardError": {},
    "lblTigerCardRequired": {},
    "lblValidationMessage": {},
    "lblWelcome": {},
    "Method_DataCard1": {},
    "Notes_DataCard1": {},
    "Printer_DataCard1": {},
    "ProjectType_DataCard1": {},
    "recCancelModal": {},
    "recCancelOverlay": {},
    "recCardBg": {},
    "recConfirmModal": {},
    "recConfirmOverlay": {},
    "recHeaderBg": {},
    "recHeaderBg2": {},
    "recHeaderBgHome": {},
    "recLoadingBg": {},
    "recLoadingOverlay": {},
    "recNavBg": {},
    "recNavBg2": {},
    "recNavBgHome": {},
    "scrHome": {},
    "scrMyRequests": {},
    "scrSubmit": {},
    "StarVisible1": {},
    "StarVisible10": {},
    "StarVisible11": {},
    "StarVisible12": {},
    "StarVisible13": {},
    "StarVisible2": {},
    "StarVisible3": {},
    "StarVisible31": {},
    "StarVisible32": {},
    "StarVisible4": {},
    "StarVisible5": {},
    "StarVisible6": {},
    "StarVisible7": {},
    "StarVisible8": {},
    "StarVisible9": {},
    "Status_DataCard1": {},
    "Student_DataCard1": {},
    "StudentEmail_DataCard1": {},
    "StudentEntraId_DataCard1": {},
    "TigerCardNumber_DataCard1": {},
    "Title_DataCard1": {}
  },
  "PCFDynamicSchemaForIRRetrievalEntry": {},
  "PCFTemplateEntry": {},
  "PublishOrderIndices": {
    "App": 0,
    "Attachments_DataCard1": 111,
    "btnCancelNo": 155,
    "btnCancelRequest": 170,
    "btnCancelYes": 154,
    "btnConfirmCancel": 148,
    "btnConfirmEstimate": 169,
    "btnConfirmYes": 147,
    "btnGetStarted": 11,
    "btnNavHome": 28,
    "btnNavHome2": 136,
    "btnNavHomeActive": 20,
    "btnNavMyRequests": 30,
    "btnNavMyRequests2": 138,
    "btnNavMyRequestsHome": 22,
    "btnNavSubmit": 29,
    "btnNavSubmit2": 137,
    "btnNavSubmitHome": 21,
    "btnRefresh": 133,
    "btnStatusBadge": 161,
    "btnSubmit": 129,
    "btnViewRequests": 16,
    "cirColorPreview": 99,
    "cirColorPreviewBackdrop": 98,
    "cirPrintColorBackdrop": 164,
    "cirPrintColorDot": 165,
    "Color_DataCard1": 93,
    "conActionCards": 6,
    "conCancelModal": 149,
    "conConfirmModal": 139,
    "conFormArea": 35,
    "conGalleryArea": 157,
    "conHeader": 23,
    "conHeader2": 130,
    "conHeaderHome": 0,
    "conLoadingOverlay": 31,
    "conNavBar": 26,
    "conNavBar2": 134,
    "conNavBarHome": 18,
    "conRequestsCard": 12,
    "conSubmitCard": 7,
    "conWelcome": 3,
    "Course Number_DataCard1": 69,
    "DataCardKey1": 41,
    "DataCardKey10": 88,
    "DataCardKey11": 103,
    "DataCardKey12": 108,
    "DataCardKey13": 120,
    "DataCardKey2": 125,
    "DataCardKey3": 46,
    "DataCardKey31": 57,
    "DataCardKey32": 113,
    "DataCardKey4": 52,
    "DataCardKey5": 71,
    "DataCardKey6": 65,
    "DataCardKey7": 76,
    "DataCardKey8": 81,
    "DataCardKey9": 95,
    "DataCardValue1": 42,
    "DataCardValue10": 90,
    "DataCardValue11": 104,
    "DataCardValue12": 109,
    "DataCardValue13": 121,
    "DataCardValue2": 126,
    "DataCardValue3": 47,
    "DataCardValue30": 59,
    "DataCardValue31": 116,
    "DataCardValue4": 53,
    "DataCardValue5": 72,
    "DataCardValue6": 67,
    "DataCardValue7": 77,
    "DataCardValue8": 83,
    "DataCardValue9": 97,
    "dcImportantInfo": 37,
    "Discipline_DataCard1": 63,
    "DueDate_DataCard1": 101,
    "ErrorMessage1": 43,
    "ErrorMessage10": 91,
    "ErrorMessage11": 105,
    "ErrorMessage12": 110,
    "ErrorMessage13": 122,
    "ErrorMessage2": 127,
    "ErrorMessage3": 49,
    "ErrorMessage31": 60,
    "ErrorMessage32": 117,
    "ErrorMessage4": 54,
    "ErrorMessage5": 73,
    "ErrorMessage6": 68,
    "ErrorMessage7": 78,
    "ErrorMessage8": 84,
    "ErrorMessage9": 100,
    "frmSubmit": 36,
    "galleryTemplate1": 159,
    "galMyRequests": 158,
    "Host": 0,
    "icnRequests": 13,
    "icnSubmit": 8,
    "imgTigerCardExample": 62,
    "Label1": 66,
    "lblAttachmentsRequired": 115,
    "lblCancelMessage": 153,
    "lblCancelTitle": 151,
    "lblColorRequired": 96,
    "lblConfirmCost": 143,
    "lblConfirmDetails": 145,
    "lblConfirmReqKey": 142,
    "lblConfirmTitle": 141,
    "lblConfirmWarning": 146,
    "lblDimensionsWarning": 92,
    "lblEmptyState": 156,
    "lblEstimate": 167,
    "lblFileWarning": 114,
    "lblHeaderTitle": 25,
    "lblHeaderTitle2": 132,
    "lblHeaderTitleHome": 2,
    "lblHelpText": 17,
    "lblImportantInfo": 38,
    "lblLoadingText": 34,
    "lblMethodInfo": 85,
    "lblMethodRequired": 82,
    "lblPrintDetails": 166,
    "lblPrinterRequired": 89,
    "lblReqKey": 162,
    "lblRequestsDesc": 15,
    "lblRequestsTitle": 14,
    "lblStatusMessage": 168,
    "lblStudentName": 48,
    "lblSubmitDate": 163,
    "lblSubmitDesc": 10,
    "lblSubmitTitle": 9,
    "lblSubtitle": 5,
    "lblTigerCardError": 61,
    "lblTigerCardRequired": 58,
    "lblValidationMessage": 128,
    "lblWelcome": 4,
    "Method_DataCard1": 79,
    "Notes_DataCard1": 106,
    "Printer_DataCard1": 86,
    "ProjectType_DataCard1": 74,
    "recCancelModal": 150,
    "recCancelOverlay": 152,
    "recCardBg": 160,
    "recConfirmModal": 140,
    "recConfirmOverlay": 144,
    "recHeaderBg": 24,
    "recHeaderBg2": 131,
    "recHeaderBgHome": 1,
    "recLoadingBg": 33,
    "recLoadingOverlay": 32,
    "recNavBg": 27,
    "recNavBg2": 135,
    "recNavBgHome": 19,
    "scrHome": 0,
    "scrMyRequests": 0,
    "scrSubmit": 0,
    "StarVisible1": 40,
    "StarVisible10": 87,
    "StarVisible11": 102,
    "StarVisible12": 107,
    "StarVisible13": 119,
    "StarVisible2": 124,
    "StarVisible3": 45,
    "StarVisible31": 56,
    "StarVisible32": 112,
    "StarVisible4": 51,
    "StarVisible5": 70,
    "StarVisible6": 64,
    "StarVisible7": 75,
    "StarVisible8": 80,
    "StarVisible9": 94,
    "Status_DataCard1": 118,
    "Student_DataCard1": 44,
    "StudentEmail_DataCard1": 50,
    "StudentEntraId_DataCard1": 123,
    "TigerCardNumber_DataCard1": 55,
    "Title_DataCard1": 39
  },
  "ResourcesJsonIndices": {
    "Image-SampleImage": 1,
    "Image-Tiger Card": 0,
    "Image-TigerCard": 2
  },
  "RuleScreenIdWithoutScreen": {},
  "TemplateVersions": {},
  "VolatileProperties": {
    "AnalysisLoadTime": 1.5493364000000001,
    "ControlCount": {
      "attachments": 1,
      "button": 20,
      "circle": 4,
      "combobox": 7,
      "datepicker": 1,
      "form": 1,
      "gallery": 1,
      "galleryTemplate": 1,
      "groupContainer": 15,
      "icon": 2,
      "image": 1,
      "label": 82,
      "rectangle": 13,
      "screen": 3,
      "text": 6,
      "typedDataCard": 16
    },
    "DeserializationLoadTime": 0.87196899999999999
  },
  "WasLocalDatabaseReferencesEmpty": true
}